{
  "collectionName": "components_article_sources",
  "info": {
    "name": "reference",
    "icon": "link",
    "description": ""
  },
  "options": {},
  "attributes": {
    "reference_title": {
      "type": "string",
      "required": true,
      "maxLength": 36
    },
    "reference_url": {
      "type": "string",
      "required": true
    },
    "reference_description": {
      "type": "richtext",
      "required": true,
      "minLength": 40
    },
    "reference_button_text": {
      "type": "string",
      "required": true,
      "maxLength": 30
    }
  }
}
